README.rst
setup.py
yamlord/__init__.py
yamlord/yamio.py
yamlord.egg-info/PKG-INFO
yamlord.egg-info/SOURCES.txt
yamlord.egg-info/dependency_links.txt
yamlord.egg-info/not-zip-safe
yamlord.egg-info/requires.txt
yamlord.egg-info/top_level.txt